AUTHORS.rst
CONTRIBUTING.rst
HISTORY.rst
LICENSE
MANIFEST.in
README.rst
setup.py
librarian/__init__.py
librarian/card.py
librarian/deck.py
librarian/library.py
librarian.egg-info/PKG-INFO
librarian.egg-info/SOURCES.txt
librarian.egg-info/dependency_links.txt
librarian.egg-info/not-zip-safe
librarian.egg-info/top_level.txt
test/test_card.py