Metadata-Version: 1.1
Name: librarian
Version: 0.3.0
Summary: Python advanced card game library.
Home-page: https://github.com/Nekroze/librarian
Author: Taylor "Nekroze" Lawson
Author-email: nekroze@eturnilnetwork.com
License: MIT
Keywords: librarian
Platform: UNKNOWN
Classifier: Development Status :: 3 - Alpha
Classifier: Intended Audience :: Developers
Classifier: License :: OSI Approved :: MIT License
Classifier: Natural Language :: English
Classifier: Programming Language :: Python :: 2
Classifier: Programming Language :: Python :: 2.6
Classifier: Programming Language :: Python :: 2.7
Classifier: Programming Language :: Python :: 3
Classifier: Programming Language :: Python :: 3.3
Classifier: Programming Language :: Python :: Implementation :: PyPy
Classifier: Topic :: Games/Entertainment
